README.md
setup.cfg
setup.py
src/rbp/__init__.py
src/rbp.egg-info/PKG-INFO
src/rbp.egg-info/SOURCES.txt
src/rbp.egg-info/dependency_links.txt
src/rbp.egg-info/requires.txt
src/rbp.egg-info/top_level.txt
src/rbp/encoding/__init__.py
src/rbp/encoding/dot_matrix.py
src/rbp/encoding/one_hot.py
src/rbp/preprocessing/__init__.py
src/rbp/preprocessing/bed2cons.py
src/rbp/preprocessing/bed2fa.py
src/rbp/random/__init__.py
src/rbp/random/genomic_position.py
src/rbp/random/random_intervals.py
src/rbp/random/random_sequence.py
src/rbp/random/seq_permutation.py
src/rbp/utils/__init__.py
src/rbp/utils/options.py
src/rbp/utils/storage.py