Metadata-Version: 1.1
Name: rbp
Version: 0.1.2
Summary: Python utils of RBP Bioinformatics.
Home-page: https://gitlab.com/RBP_Bioinformatics/rbp
Author: RBP Bioinformatics
Author-email: lamparna@gmail.com
License: MIT
Download-URL: https://gitlab.com/RBP_Bioinformatics/rbp/-/archive/master/rbp-master.tar.gz
Keywords: bioinformatics,genome,dna
Platform: UNKNOWN
Classifier: Development Status :: 3 - Alpha
Classifier: Intended Audience :: Developers
Classifier: Topic :: Software Development :: Build Tools
Classifier: License :: OSI Approved :: MIT License
Classifier: Programming Language :: Python :: 3
Classifier: Programming Language :: Python :: 3.4
Classifier: Programming Language :: Python :: 3.5
Classifier: Programming Language :: Python :: 3.6
Classifier: Programming Language :: Python :: 3.7
Classifier: Programming Language :: Python :: 3.8
